flask_easymde/__init__.py
flask_easymde/static/easymde.min.css
flask_easymde/static/easymde.min.js
Flask_EasyMDE-1.0.dist-info/LICENSE.txt
Flask_EasyMDE-1.0.dist-info/METADATA
Flask_EasyMDE-1.0.dist-info/WHEEL
Flask_EasyMDE-1.0.dist-info/top_level.txt
Flask_EasyMDE-1.0.dist-info/RECORD
